{"type":"FeatureCollection","features":[{"type":"Feature","properties":{"@id":"way/63639781","building":"apartments","building:levels":"6","roof:levels":"1","source":"cadastre-dgi-fr source : Direction Générale des Impôts - Cadastre. Mise à jour : 2010","id":"way/63639781"},"geometry":{"type":"Polygon","coordinates":[[[2.3692467,48.8550525],[2.3692372,48.8550513],[2.3691396,48.8550413],[2.3691605,48.8549566],[2.3689447,48.8549354],[2.3689614,48.8548655],[2.3689647,48.8548518],[2.3690431,48.8548608],[2.3691075,48.854868],[2.3691223,48.8548697],[2.3692932,48.8548891],[2.3693218,48.8548922],[2.3694054,48.8549016],[2.3693824,48.8549835],[2.3693597,48.8550642],[2.3692467,48.8550525]]]},"id":"way/63639781"},{"type":"Feature","properties":{"@id":"way/49429177","cycleway:left":"lane","cycleway:left:lane":"exclusive","cycleway:left:oneway":"-1","cycleway:right":"no","highway":"residential","lit":"yes","maxspeed":"30","name":"Rue Amelot","name:etymology:wikidata":"Q674816","oneway":"yes","oneway:bicycle":"no","sidewalk:both":"separate","smoothness":"good","surface":"asphalt","zone:maxspeed":"FR:30","id":"way/49429177"},"geometry":{"type":"LineString","coordinates":[[2.3696039,48.854881],[2.3695096,48.8549013],[2.3692185,48.8558489],[2.3692026,48.8559257]]},"id":"way/49429177"},{"type":"Feature","properties":{"@id":"way/123486075","busway:both":"lane","cycleway:both":"share_busway","enforcement:operator":"Police nationale","highway":"primary","lanes":"5","lanes:backward":"3","lanes:forward":"2","lit":"yes","maxspeed":"30","name":"Boulevard Beaumarchais","name:etymology:wikidata":"Q70326","name:zh":"博马舍大道","operator":"Ville de Paris","operator:authority":"Maire de Paris après avis du préfet de police","operator:authority:related_law":"IV de l'article L. 2512-14 du code général des collectivités territoriales","operator:url":"https://cdn.paris.fr/paris/2020/02/26/5bf469a311d0beb9911e92d113781550.ai","sidewalk:both":"separate","smoothness":"good","surface":"asphalt","id":"way/123486075"},"geometry":{"type":"LineString","coordinates":[[2.3689521,48.8540242],[2.3688961,48.854164],[2.3688648,48.8542528],[2.3688476,48.8543265],[2.3688224,48.854435],[2.3688167,48.8544593],[2.3687831,48.8546035],[2.3687336,48.8548148],[2.3687021,48.8549511],[2.3686014,48.8553833],[2.3685253,48.8557101],[2.3685101,48.855775],[2.3684984,48.8558253]]},"id":"way/123486075"},{"type":"Feature","properties":{"@id":"way/624810217","access:conditional":"no @ (Su, Th 07:00-14:30)","cycleway":"on_street","cycleway:surface":"asphalt","footway:surface":"paving_stones","highway":"cycleway","lit":"yes","name":"Boulevard Richard-Lenoir","name:etymology:wikidata":"Q3085685","oneway":"yes","segregated":"yes","surface":"asphalt","traffic_sign":"FR:C113","id":"way/624810217"},"geometry":{"type":"LineString","coordinates":[[2.369874,48.8552953],[2.3698576,48.8552592],[2.3696791,48.8548649],[2.3696405,48.8547801],[2.3693223,48.8540768]]},"id":"way/624810217"},{"type":"Feature","properties":{"@id":"way/662350056","cycleway:left":"no","cycleway:right":"separate","dual_carriageway":"yes","highway":"residential","lanes":"2","lit":"yes","maxspeed":"30","name":"Boulevard Richard-Lenoir","name:etymology:wikidata":"Q3085685","oneway":"yes","sidewalk":"separate","surface":"asphalt","id":"way/662350056"},"geometry":{"type":"LineString","coordinates":[[2.3698925,48.8555157],[2.3698326,48.8553837],[2.3697855,48.8552742],[2.3696039,48.854881],[2.3695645,48.8547948],[2.3692575,48.8541302]]},"id":"way/662350056"},{"type":"Feature","properties":{"@id":"way/1190197148","footway":"sidewalk","highway":"footway","lit":"yes","surface":"asphalt","id":"way/1190197148"},"geometry":{"type":"LineString","coordinates":[[2.3683489,48.8556956],[2.3685253,48.8549371],[2.368586,48.854942]]},"id":"way/1190197148"},{"type":"Feature","properties":{"@id":"way/1190407382","footway":"sidewalk","highway":"footway","lit":"yes","surface":"paving_stones","id":"way/1190407382"},"geometry":{"type":"LineString","coordinates":[[2.3694624,48.8548068],[2.3694487,48.8548026],[2.369155,48.8558401],[2.3691392,48.8558537]]},"id":"way/1190407382"},{"type":"Feature","properties":{"@id":"way/1190764957","crossing":"uncontrolled","crossing:markings":"zebra","crossing:signals":"no","footway":"crossing","highway":"footway","lit":"yes","surface":"asphalt","id":"way/1190764957"},"geometry":{"type":"LineString","coordinates":[[2.3694624,48.8548068],[2.3694659,48.8548138],[2.3695096,48.8549013],[2.369565,48.8550121]]},"id":"way/1190764957"},{"type":"Feature","properties":{"@id":"way/1307555130","footway":"sidewalk","highway":"footway","lit":"yes","surface":"paving_stones","id":"way/1307555130"},"geometry":{"type":"LineString","coordinates":[[2.3692175,48.853784],[2.3692734,48.8539359],[2.3693516,48.8540129],[2.3693672,48.854058],[2.369489,48.8542673],[2.3697079,48.854767],[2.3699173,48.8552451]]},"id":"way/1307555130"}]}