{"type":"FeatureCollection","features":[{"type":"Feature","properties":{"@id":"way/63971242","building":"yes","building:levels":"2","source":"cadastre-dgi-fr source : Direction Générale des Impôts - Cadastre. Mise à jour : 2010","wall":"no","id":"way/63971242"},"geometry":{"type":"Polygon","coordinates":[[[2.3936002,48.8951407],[2.3937491,48.8948402],[2.3938297,48.8948577],[2.3936753,48.8951563],[2.3936002,48.8951407]]]},"id":"way/63971242"},{"type":"Feature","properties":{"@id":"way/30168413","cycleway:both":"no","highway":"primary","lanes":"4","lit":"yes","maxspeed":"50","name":"Boulevard Sérurier","name:etymology:wikidata":"Q376344","sidewalk:both":"separate","surface":"asphalt","id":"way/30168413"},"geometry":{"type":"LineString","coordinates":[[2.3941589,48.8952584],[2.3941807,48.895218],[2.3942742,48.8949724],[2.3943399,48.8947728],[2.3943766,48.8946355],[2.3944871,48.894205],[2.3945887,48.8937897]]},"id":"way/30168413"},{"type":"Feature","properties":{"@id":"way/93742443","cycleway":"sidewalk","highway":"cycleway","lit":"yes","name":"Boulevard Sérurier","name:etymology:wikidata":"Q376344","surface":"asphalt","width":"2.3","id":"way/93742443"},"geometry":{"type":"LineString","coordinates":[[2.3952663,48.8905486],[2.3952422,48.8906519],[2.3948929,48.8920506],[2.3948078,48.8924421],[2.3947433,48.8927089],[2.3944639,48.8938647],[2.3942336,48.8947854],[2.3941681,48.8949744],[2.3940814,48.8951685]]},"id":"way/93742443"},{"type":"Feature","properties":{"@id":"way/1193579437","footway":"sidewalk","highway":"footway","lit":"yes","id":"way/1193579437"},"geometry":{"type":"LineString","coordinates":[[2.3942499,48.8953076],[2.3942905,48.8952281],[2.3944053,48.8949679],[2.3945488,48.8944772],[2.3948814,48.8930872],[2.3949525,48.8929206],[2.3950209,48.8928077],[2.3951523,48.8926455]]},"id":"way/1193579437"},{"type":"Feature","properties":{"@id":"way/1193579495","footway":"sidewalk","highway":"footway","lit":"yes","id":"way/1193579495"},"geometry":{"type":"LineString","coordinates":[[2.3940103,48.8951813],[2.3940157,48.8951381],[2.394127,48.8948343],[2.3941961,48.8945773],[2.3942504,48.894371],[2.3944113,48.8937265],[2.3946239,48.8928699],[2.3946677,48.8926867],[2.394813,48.8920781],[2.3948535,48.8919194],[2.3949183,48.891665],[2.3950691,48.8910654],[2.395165,48.8905945],[2.3951831,48.8905663],[2.3952214,48.8905579],[2.3952214,48.8905447]]},"id":"way/1193579495"},{"type":"Feature","properties":{"@id":"node/8168820993","natural":"tree","id":"node/8168820993"},"geometry":{"type":"Point","coordinates":[2.3944062,48.8949067]},"id":"node/8168820993"},{"type":"Feature","properties":{"@id":"node/8168820994","genus":"Styphnolobium","natural":"tree","species":"Styphnolobium japonicum","id":"node/8168820994"},"geometry":{"type":"Point","coordinates":[2.3941582,48.8948539]},"id":"node/8168820994"},{"type":"Feature","properties":{"@id":"node/8168820995","genus":"Styphnolobium","natural":"tree","species":"Styphnolobium japonicum","id":"node/8168820995"},"geometry":{"type":"Point","coordinates":[2.3941942,48.8947315]},"id":"node/8168820995"},{"type":"Feature","properties":{"@id":"node/8168820996","genus":"Styphnolobium","natural":"tree","species":"Styphnolobium japonicum","id":"node/8168820996"},"geometry":{"type":"Point","coordinates":[2.3942154,48.8946635]},"id":"node/8168820996"},{"type":"Feature","properties":{"@id":"node/8168820997","genus":"Styphnolobium","natural":"tree","species":"Styphnolobium japonicum","id":"node/8168820997"},"geometry":{"type":"Point","coordinates":[2.3942328,48.894598]},"id":"node/8168820997"},{"type":"Feature","properties":{"@id":"node/8168820998","genus":"Styphnolobium","natural":"tree","species":"Styphnolobium japonicum","id":"node/8168820998"},"geometry":{"type":"Point","coordinates":[2.3942469,48.8945343]},"id":"node/8168820998"},{"type":"Feature","properties":{"@id":"node/11897857332","highway":"street_lamp","id":"node/11897857332"},"geometry":{"type":"Point","coordinates":[2.3941803,48.894776]},"id":"node/11897857332"},{"type":"Feature","properties":{"@id":"node/11897857333","highway":"street_lamp","id":"node/11897857333"},"geometry":{"type":"Point","coordinates":[2.3944375,48.894777]},"id":"node/11897857333"},{"type":"Feature","properties":{"@id":"node/11897857334","highway":"street_lamp","id":"node/11897857334"},"geometry":{"type":"Point","coordinates":[2.3942389,48.8945454]},"id":"node/11897857334"}]}