{"type":"FeatureCollection","features":[{"type":"Feature","properties":{"@id":"way/63232864","building":"yes","leisure":"sports_centre","name":"Piscine Fernand-Blanluet","operator":"Est Ensemble","operator:type":"public","source":"cadastre-dgi-fr source : Direction Générale des Impôts - Cadastre. Mise à jour : 2010","sport":"swimming","id":"way/63232864"},"geometry":{"type":"Polygon","coordinates":[[[2.3995464,48.8843696],[2.3996999,48.8844507],[2.3997042,48.8844484],[2.399725,48.8844589],[2.3996806,48.8844947],[2.3996959,48.8845048],[2.3996451,48.8846138],[2.3993868,48.8848209],[2.3993322,48.8848172],[2.399289,48.8848102],[2.3992531,48.8848015],[2.3992051,48.8847867],[2.3991812,48.8847773],[2.3991541,48.884765],[2.3991037,48.8847362],[2.3993165,48.8845638],[2.3993076,48.8845591],[2.3995464,48.8843696]]]},"id":"way/63232864"},{"type":"Feature","properties":{"@id":"way/73247557","building":"shed","source":"cadastre-dgi-fr source : Direction Générale des Impôts - Cadastre. Mise à jour : 2010","id":"way/73247557"},"geometry":{"type":"Polygon","coordinates":[[[2.3996705,48.8852953],[2.3996975,48.885293],[2.3997011,48.8853108],[2.3996742,48.8853131],[2.3996705,48.8852953]]]},"id":"way/73247557"},{"type":"Feature","properties":{"@id":"way/73248595","building":"apartments","source":"cadastre-dgi-fr source : Direction Générale des Impôts - Cadastre. Mise à jour : 2010","id":"way/73248595"},"geometry":{"type":"Polygon","coordinates":[[[2.3998499,48.8845875],[2.3999222,48.8847955],[2.3997878,48.8848081],[2.3997037,48.8846077],[2.3998499,48.8845875]]]},"id":"way/73248595"},{"type":"Feature","properties":{"@id":"way/73248718","building":"service","source":"cadastre-dgi-fr source : Direction Générale des Impôts - Cadastre. Mise à jour : 2010","id":"way/73248718"},"geometry":{"type":"Polygon","coordinates":[[[2.3996687,48.8852864],[2.3996705,48.8852953],[2.3996742,48.8853131],[2.3996784,48.8853338],[2.399609,48.88534],[2.3995987,48.885291],[2.3996687,48.8852864]]]},"id":"way/73248718"},{"type":"Feature","properties":{"@id":"way/156857316","cycleway:both":"lane","cycleway:both:lane":"exclusive","highway":"residential","lit":"yes","maxspeed":"30","name":"Rue Sigmund Freud","name:etymology:wikidata":"Q9215","sidewalk:both":"separate","sidewalk:both:surface":"asphalt","smoothness":"good","surface":"asphalt","width":"9.5","id":"way/156857316"},"geometry":{"type":"LineString","coordinates":[[2.398808,48.8846878],[2.3989225,48.8845877],[2.3989964,48.8845235],[2.3996267,48.8840204],[2.399658,48.883995],[2.3998772,48.8838176],[2.401501,48.8825107],[2.401834,48.8823474],[2.4022347,48.8821437],[2.4022771,48.8821225],[2.4023544,48.8820841],[2.4024313,48.8820432],[2.4024945,48.8820103]]},"id":"way/156857316"},{"type":"Feature","properties":{"@id":"way/864164189","cycleway:left":"opposite_lane","highway":"residential","lit":"yes","maxspeed":"30","name":"Rue Jean-Baptiste Sémanaz","name:etymology:wikidata":"Q64526346","oneway":"yes","oneway:bicycle":"no","sidewalk":"both","surface":"asphalt","id":"way/864164189"},"geometry":{"type":"LineString","coordinates":[[2.4017374,48.8846686],[2.4010611,48.8847338],[2.4004843,48.8847873],[2.4004153,48.8847937],[2.4002672,48.8848072],[2.3999623,48.8848349],[2.3997928,48.8848489]]},"id":"way/864164189"},{"type":"Feature","properties":{"@id":"way/864173452","highway":"residential","lanes":"2","lit":"yes","maxspeed":"30","name":"Rue Jean-Baptiste Sémanaz","name:etymology:wikidata":"Q64526346","oneway":"no","sidewalk":"both","surface":"asphalt","id":"way/864173452"},"geometry":{"type":"LineString","coordinates":[[2.3995508,48.884869],[2.3993103,48.8848889],[2.3992085,48.8848917],[2.3991291,48.88488],[2.398949,48.8847722],[2.3989015,48.8847438],[2.398808,48.8846878]]},"id":"way/864173452"},{"type":"Feature","properties":{"@id":"way/1154473481","highway":"residential","lanes":"2","lit":"yes","maxspeed":"30","name":"Rue Jean-Baptiste Sémanaz","name:etymology:wikidata":"Q64526346","oneway":"no","sidewalk":"both","surface":"asphalt","id":"way/1154473481"},"geometry":{"type":"LineString","coordinates":[[2.3997928,48.8848489],[2.3995508,48.884869]]},"id":"way/1154473481"},{"type":"Feature","properties":{"@id":"way/1239467971","footway":"sidewalk","highway":"footway","lit":"yes","surface":"asphalt","id":"way/1239467971"},"geometry":{"type":"LineString","coordinates":[[2.3988801,48.8847666],[2.3988519,48.8847952],[2.398834,48.8848133],[2.3984125,48.8852405],[2.398143,48.8856356],[2.3981436,48.8857749],[2.3981889,48.8858642],[2.3982348,48.8858794],[2.3982731,48.8858874],[2.3982808,48.8859086]]},"id":"way/1239467971"},{"type":"Feature","properties":{"@id":"way/1239467972","footway":"sidewalk","highway":"footway","lit":"yes","surface":"asphalt","id":"way/1239467972"},"geometry":{"type":"LineString","coordinates":[[2.4000551,48.8837938],[2.3997562,48.8840382],[2.3990278,48.8846337],[2.3989696,48.8846813],[2.3989287,48.8847148]]},"id":"way/1239467972"},{"type":"Feature","properties":{"@id":"way/1239515830","footway":"sidewalk","highway":"footway","lit":"yes","surface":"asphalt","id":"way/1239515830"},"geometry":{"type":"LineString","coordinates":[[2.3990278,48.8846337],[2.3989798,48.884612]]},"id":"way/1239515830"},{"type":"Feature","properties":{"@id":"way/1239515832","footway":"sidewalk","highway":"footway","lit":"yes","surface":"asphalt","id":"way/1239515832"},"geometry":{"type":"LineString","coordinates":[[2.3986315,48.8847306],[2.3986643,48.8847438]]},"id":"way/1239515832"},{"type":"Feature","properties":{"@id":"way/1239515833","footway":"sidewalk","highway":"footway","lit":"yes","surface":"asphalt","id":"way/1239515833"},"geometry":{"type":"LineString","coordinates":[[2.398834,48.8848133],[2.3987813,48.8847914]]},"id":"way/1239515833"},{"type":"Feature","properties":{"@id":"way/1239515834","crossing":"traffic_signals","crossing:island":"no","crossing:markings":"zebra","footway":"crossing","highway":"footway","lit":"yes","surface":"sett","id":"way/1239515834"},"geometry":{"type":"LineString","coordinates":[[2.3986643,48.8847438],[2.3987265,48.8847691],[2.3987813,48.8847914]]},"id":"way/1239515834"},{"type":"Feature","properties":{"@id":"way/1239515835","crossing":"traffic_signals","crossing:island":"no","crossing:markings":"zebra","footway":"crossing","highway":"footway","lit":"yes","surface":"asphalt","id":"way/1239515835"},"geometry":{"type":"LineString","coordinates":[[2.3989287,48.8847148],[2.3989015,48.8847438],[2.3988801,48.8847666]]},"id":"way/1239515835"},{"type":"Feature","properties":{"@id":"way/1239515836","crossing":"traffic_signals","footway":"crossing","highway":"footway","lit":"yes","surface":"sett","id":"way/1239515836"},"geometry":{"type":"LineString","coordinates":[[2.3988628,48.8845623],[2.3989225,48.8845877],[2.3989798,48.884612]]},"id":"way/1239515836"},{"type":"Feature","properties":{"@id":"way/1239515837","footway":"sidewalk","highway":"footway","lit":"yes","surface":"asphalt","id":"way/1239515837"},"geometry":{"type":"LineString","coordinates":[[2.3977595,48.885971],[2.3979083,48.8856285],[2.3980115,48.8854508],[2.3981698,48.8852282],[2.3983374,48.8850271],[2.3986315,48.8847306],[2.3988336,48.8845493],[2.3990998,48.8843262],[2.3995124,48.8839982],[2.3995682,48.8839555],[2.3995853,48.8839419],[2.4003531,48.8833308],[2.4007434,48.8830186],[2.4013066,48.8825701],[2.4014528,48.8824533],[2.4016312,48.882362],[2.4022809,48.8820357]]},"id":"way/1239515837"},{"type":"Feature","properties":{"@id":"way/1408810490","cycleway:both":"lane","cycleway:both:lane":"exclusive","highway":"residential","lit":"yes","maxspeed":"30","name":"Rue Sigmund Freud","name:etymology:wikidata":"Q9215","sidewalk:both":"separate","sidewalk:both:surface":"asphalt","smoothness":"good","surface":"sett","width":"9.5","id":"way/1408810490"},"geometry":{"type":"LineString","coordinates":[[2.3980967,48.8859778],[2.3980751,48.8859255],[2.398062,48.8858988],[2.3980375,48.8858429],[2.3980185,48.8857738],[2.3980154,48.8856648],[2.3980464,48.8855858],[2.3980913,48.8855055],[2.3983428,48.8851682],[2.3984531,48.8850414],[2.3987265,48.8847691],[2.398808,48.8846878]]},"id":"way/1408810490"},{"type":"Feature","properties":{"@id":"way/1420231198","crossing":"uncontrolled","crossing:island":"no","crossing:markings":"zebra","footway":"crossing","highway":"footway","traffic_calming":"table","id":"way/1420231198"},"geometry":{"type":"LineString","coordinates":[[2.3993142,48.8849192],[2.3993103,48.8848889],[2.3993063,48.8848571]]},"id":"way/1420231198"},{"type":"Feature","properties":{"@id":"way/1420231199","footway":"sidewalk","highway":"footway","id":"way/1420231199"},"geometry":{"type":"LineString","coordinates":[[2.3989696,48.8846813],[2.3991479,48.8848064],[2.3991848,48.8848296],[2.3992334,48.8848416],[2.399304,48.8848391]]},"id":"way/1420231199"},{"type":"Feature","properties":{"@id":"way/1420231200","footway":"sidewalk","highway":"footway","id":"way/1420231200"},"geometry":{"type":"LineString","coordinates":[[2.3993178,48.8849482],[2.3991597,48.8849557],[2.3990951,48.8849471],[2.3990168,48.8849154],[2.3989203,48.8848498],[2.3988519,48.8847952]]},"id":"way/1420231200"},{"type":"Feature","properties":{"@id":"way/1420231201","footway":"sidewalk","highway":"footway","id":"way/1420231201"},"geometry":{"type":"LineString","coordinates":[[2.399304,48.8848391],[2.3993063,48.8848571]]},"id":"way/1420231201"},{"type":"Feature","properties":{"@id":"way/1420231202","footway":"sidewalk","highway":"footway","id":"way/1420231202"},"geometry":{"type":"LineString","coordinates":[[2.3993142,48.8849192],[2.3993178,48.8849482]]},"id":"way/1420231202"},{"type":"Feature","properties":{"@id":"way/1427924644","footway":"sidewalk","highway":"footway","id":"way/1427924644"},"geometry":{"type":"LineString","coordinates":[[2.3993178,48.8849482],[2.3995099,48.8849485],[2.4002852,48.8848764],[2.4003194,48.8848733],[2.4003583,48.8848816],[2.4003764,48.8849005],[2.4004131,48.8850817],[2.4004669,48.8852984],[2.4004797,48.8853733],[2.4005299,48.8856251],[2.4005179,48.8856545]]},"id":"way/1427924644"},{"type":"Feature","properties":{"@id":"node/320907529","highway":"traffic_signals","traffic_signals":"signal","traffic_signals:direction":"both","id":"node/320907529"},"geometry":{"type":"Point","coordinates":[2.398808,48.8846878]},"id":"node/320907529"},{"type":"Feature","properties":{"@id":"node/8093676606","natural":"tree","id":"node/8093676606"},"geometry":{"type":"Point","coordinates":[2.3997417,48.8848972]},"id":"node/8093676606"},{"type":"Feature","properties":{"@id":"node/8093676607","natural":"tree","id":"node/8093676607"},"geometry":{"type":"Point","coordinates":[2.3998519,48.8848867]},"id":"node/8093676607"},{"type":"Feature","properties":{"@id":"node/8093676608","natural":"tree","id":"node/8093676608"},"geometry":{"type":"Point","coordinates":[2.3999328,48.8848811]},"id":"node/8093676608"},{"type":"Feature","properties":{"@id":"node/8093676613","natural":"tree","id":"node/8093676613"},"geometry":{"type":"Point","coordinates":[2.3992834,48.8849452]},"id":"node/8093676613"},{"type":"Feature","properties":{"@id":"node/8093676614","natural":"tree","id":"node/8093676614"},"geometry":{"type":"Point","coordinates":[2.3991394,48.8849419]},"id":"node/8093676614"},{"type":"Feature","properties":{"@id":"node/8093676615","natural":"tree","id":"node/8093676615"},"geometry":{"type":"Point","coordinates":[2.3989734,48.8848569]},"id":"node/8093676615"},{"type":"Feature","properties":{"@id":"node/8098468813","addr:city":"Le Pré-Saint-Gervais","addr:housenumber":"29","addr:postcode":"93310","addr:street":"Rue Jean-Baptiste Sémanaz","name":"Chocolaterie des Lions","opening_hours":"Tu-Sa 10:00-13:00,15:00-19:00","shop":"chocolate","id":"node/8098468813"},"geometry":{"type":"Point","coordinates":[2.3998404,48.8847874]},"id":"node/8098468813"},{"type":"Feature","properties":{"@id":"node/8108756284","natural":"tree","id":"node/8108756284"},"geometry":{"type":"Point","coordinates":[2.3987487,48.8854002]},"id":"node/8108756284"},{"type":"Feature","properties":{"@id":"node/8108756285","natural":"tree","id":"node/8108756285"},"geometry":{"type":"Point","coordinates":[2.3988604,48.8852437]},"id":"node/8108756285"},{"type":"Feature","properties":{"@id":"node/8108756286","natural":"tree","id":"node/8108756286"},"geometry":{"type":"Point","coordinates":[2.3989226,48.8851882]},"id":"node/8108756286"},{"type":"Feature","properties":{"@id":"node/8108756287","natural":"tree","id":"node/8108756287"},"geometry":{"type":"Point","coordinates":[2.3990958,48.8854316]},"id":"node/8108756287"},{"type":"Feature","properties":{"@id":"node/8108756288","natural":"tree","id":"node/8108756288"},"geometry":{"type":"Point","coordinates":[2.3991623,48.885426]},"id":"node/8108756288"},{"type":"Feature","properties":{"@id":"node/8108756289","natural":"tree","id":"node/8108756289"},"geometry":{"type":"Point","coordinates":[2.3991725,48.8853738]},"id":"node/8108756289"},{"type":"Feature","properties":{"@id":"node/8108756290","natural":"tree","id":"node/8108756290"},"geometry":{"type":"Point","coordinates":[2.3990923,48.8853727]},"id":"node/8108756290"},{"type":"Feature","properties":{"@id":"node/8108756291","natural":"tree","id":"node/8108756291"},"geometry":{"type":"Point","coordinates":[2.3989491,48.8849987]},"id":"node/8108756291"},{"type":"Feature","properties":{"@id":"node/8108756295","natural":"tree","id":"node/8108756295"},"geometry":{"type":"Point","coordinates":[2.3991572,48.8854938]},"id":"node/8108756295"},{"type":"Feature","properties":{"@id":"node/11514361939","genus":"Platanus","height":"25","leaf_type":"broadleaved","natural":"tree","species":"Platanus × hispanica","species:wikidata":"Q161374","id":"node/11514361939"},"geometry":{"type":"Point","coordinates":[2.3985984,48.8849961]},"id":"node/11514361939"},{"type":"Feature","properties":{"@id":"node/11514361941","genus":"Platanus","height":"25","leaf_type":"broadleaved","natural":"tree","species":"Platanus × hispanica","species:wikidata":"Q161374","id":"node/11514361941"},"geometry":{"type":"Point","coordinates":[2.3986733,48.8849197]},"id":"node/11514361941"},{"type":"Feature","properties":{"@id":"node/11514361942","genus":"Platanus","height":"25","leaf_type":"broadleaved","natural":"tree","species":"Platanus × hispanica","species:wikidata":"Q161374","id":"node/11514361942"},"geometry":{"type":"Point","coordinates":[2.3987376,48.8848533]},"id":"node/11514361942"},{"type":"Feature","properties":{"@id":"node/11514361960","genus":"Sophora","height":"10","natural":"tree","species":"Sophora japonica","id":"node/11514361960"},"geometry":{"type":"Point","coordinates":[2.3986364,48.8847456]},"id":"node/11514361960"}]}