{"type":"FeatureCollection","features":[{"type":"Feature","properties":{"@id":"way/24036981","bicycle:lanes:backward":"designated","bus":"yes","busway:left":"opposite_lane","cycleway:left":"share_busway","cycleway:left:oneway":"-1","cycleway:right":"no","highway":"tertiary","lanes":"2","lanes:backward":"1","lanes:forward":"1","lit":"yes","maxspeed":"30","motor_vehicle":"no","name":"Rue de Turenne","name:etymology:wikidata":"Q303216","oneway":"yes","oneway:bicycle":"no","oneway:bus":"no","psv:lanes:backward":"designated","sidewalk:both":"separate","smoothness":"excellent","source:maxspeed":"FR:zone30","surface":"asphalt","id":"way/24036981"},"geometry":{"type":"LineString","coordinates":[[2.3636415,48.8554984],[2.3634821,48.8552881],[2.3633564,48.8551241],[2.3633203,48.8550744],[2.3632808,48.8550231],[2.3631421,48.8548403],[2.3630021,48.8546577],[2.3629823,48.8546361],[2.3629491,48.8545998]]},"id":"way/24036981"},{"type":"Feature","properties":{"@id":"way/124067232","access":"permissive","highway":"footway","lit":"yes","smoothness":"good","surface":"compacted","id":"way/124067232"},"geometry":{"type":"LineString","coordinates":[[2.363991,48.8548546],[2.363989,48.8548684],[2.3641807,48.8548128],[2.3642484,48.8549543],[2.3643118,48.8550866],[2.3643196,48.8550988]]},"id":"way/124067232"},{"type":"Feature","properties":{"@id":"way/230190563","access":"permissive","highway":"footway","lit":"yes","smoothness":"intermediate","source":"survey 2013","surface":"fine_gravel","id":"way/230190563"},"geometry":{"type":"LineString","coordinates":[[2.3643118,48.8550866],[2.364112,48.855127],[2.364045,48.8549974],[2.363989,48.8548684]]},"id":"way/230190563"},{"type":"Feature","properties":{"@id":"way/230190564","access":"permissive","highway":"footway","lit":"yes","smoothness":"good","source":"survey 2013","surface":"compacted","id":"way/230190564"},"geometry":{"type":"LineString","coordinates":[[2.363989,48.8548684],[2.3638027,48.8549255],[2.3638877,48.8550355],[2.3639708,48.8551491],[2.364112,48.855127]]},"id":"way/230190564"}]}